pyvuejs_cli/__init__.py
pyvuejs_cli/__main__.py
pyvuejs_cli/cli.py
pyvuejs_cli/template.zip
pyvuejs_cli-2.0.1.post1.dist-info/LICENSE
pyvuejs_cli-2.0.1.post1.dist-info/METADATA
pyvuejs_cli-2.0.1.post1.dist-info/WHEEL
pyvuejs_cli-2.0.1.post1.dist-info/entry_points.txt
pyvuejs_cli-2.0.1.post1.dist-info/top_level.txt
pyvuejs_cli-2.0.1.post1.dist-info/RECORD
