Metadata-Version: 2.1
Name: pyvuejs-cli
Version: 2.0.1.post1
Summary: pyvuejs cli
Home-page: https://github.com/eseunghwan/pyvuejs_cli
Author: eseunghwan
Author-email: shlee0920@naver.com
License: MIT license
Keywords: pyvuejs_cli
Platform: UNKNOWN
Classifier: Development Status :: 2 - Pre-Alpha
Classifier: License :: OSI Approved :: MIT License
Classifier: Natural Language :: English
Classifier: Programming Language :: Python :: 3
Requires-Python: >=3.6
